{
  "project": {
    "name": "ЖК «Северный»",
    "meta": "Генподряд · ООО «Успех» · до 30.06.2027",
    "readiness_fact": 54.71,
    "readiness_plan": 55.0,
    "delta_pp": -0.29,
    "contract_mln": 3544,
    "paid_mln": 4368,
    "workers_fact": 300,
    "workers_plan": 500,
    "supply_total_pct": 33.0
  },
  "supply": [
    {
      "name": "Инж. оборуд.",
      "pct": 50.0,
      "tone": "ok"
    },
    {
      "name": "Тех. оборуд.",
      "pct": 25.0,
      "tone": "alert"
    },
    {
      "name": "Материалы",
      "pct": 30.33,
      "tone": "default"
    },
    {
      "name": "Итого",
      "pct": 33.0,
      "tone": "default"
    }
  ],
  "finance": [
    {
      "name": "Договор · млн",
      "plan": 3544,
      "fact": 921
    },
    {
      "name": "Лимиты · млн",
      "plan": 4230,
      "fact": 1184
    },
    {
      "name": "Оплачено · млн",
      "plan": 5600,
      "fact": 4368
    }
  ],
  "labor": [
    {
      "name": "Рабочие · чел.",
      "plan": 1123,
      "fact": 863
    },
    {
      "name": "ИТР · чел.",
      "plan": 93,
      "fact": 93
    }
  ],
  "risks": [
    {
      "t": "Финансирование 489 / 1082",
      "m": "24.01"
    },
    {
      "t": "Неучтенный объём · ПСД",
      "m": "15.01"
    }
  ],
  "tasks": [
    {
      "t": "Рентабельность АО «Успех»",
      "m": "22.07",
      "status": "В работе"
    },
    {
      "t": "Стратегия ЖК «Северный»",
      "m": "10.07",
      "status": "В работе"
    },
    {
      "t": "НДС +2% · разногласия",
      "m": "26.07",
      "status": "В работе"
    },
    {
      "t": "Доп. соглашения (НДС)",
      "m": "24.07",
      "status": "В работе"
    },
    {
      "t": "Сокращение расходов",
      "m": "еженед.",
      "status": "В работе"
    },
    {
      "t": "ЖК «Солнце» · благоустр.",
      "m": "28.07",
      "status": "В работе"
    },
    {
      "t": "Контракты 1С",
      "m": "пт",
      "status": "В работе"
    },
    {
      "t": "Материалы на балансе",
      "m": "еженед.",
      "status": "В работе"
    },
    {
      "t": "Договоры с субподрядчиками",
      "m": "03.07",
      "status": "В работе"
    },
    {
      "t": "Папки с ответами · ВПР",
      "m": "пост.",
      "status": "В работе"
    },
    {
      "t": "Претензионная работа",
      "m": "пн",
      "status": "В работе"
    },
    {
      "t": "Приказ · ответственность",
      "m": "03.07",
      "status": "В работе"
    },
    {
      "t": "АО «Прут» · письмо",
      "m": "20.03",
      "status": "Не исполнено"
    },
    {
      "t": "ЖК «Берег» · справка",
      "m": "03.07",
      "status": "В работе"
    }
  ]
}
